AUTHORS.rst
CONTRIBUTING.rst
HISTORY.rst
LICENSE
MANIFEST.in
README.rst
setup.py
lazarus/__init__.py
lazarus/__main__.py
lazarus/_util.py
lazarus.egg-info/PKG-INFO
lazarus.egg-info/SOURCES.txt
lazarus.egg-info/dependency_links.txt
lazarus.egg-info/requires.txt
lazarus.egg-info/top_level.txt