Metadata-Version: 1.1
Name: lazarus
Version: 0.6.3
Summary: Restart-on-change library
Home-page: https://github.com/formwork-io/lazarus
Author: Nick Bargnesi
Author-email: nick@den-4.com
License: Apache License (2.0)
Download-URL: https://github.com/formwork-io/lazarus/releases
Platform: UNKNOWN
Classifier: Development Status :: 4 - Beta
Classifier: Intended Audience :: Developers
Classifier: Intended Audience :: Information Technology
Classifier: Intended Audience :: System Administrators
Classifier: License :: OSI Approved :: Apache Software License
Classifier: Operating System :: MacOS :: MacOS X
Classifier: Operating System :: POSIX :: Linux
Classifier: Programming Language :: Python :: 3
Classifier: Topic :: Software Development :: Libraries :: Python Modules
Classifier: Topic :: System :: Monitoring
Classifier: Topic :: Utilities
